yaqd_rgb/VERSION
yaqd_rgb/__init__.py
yaqd_rgb/__version__.py
yaqd_rgb/_rgb_qmini.py
yaqd_rgb/rgb-qmini.avpr
yaqd_rgb/rgb-qmini.toml
yaqd_rgb/rgbdriverkit/__init__.py
yaqd_rgb/rgbdriverkit/calibratedspectrometer.py
yaqd_rgb/rgbdriverkit/devicedriver.py
yaqd_rgb/rgbdriverkit/helpers.py
yaqd_rgb/rgbdriverkit/qseriesdriver.py
yaqd_rgb/rgbdriverkit/spectrometer.py
yaqd_rgb-2022.6.0.dist-info/entry_points.txt
yaqd_rgb-2022.6.0.dist-info/LICENSE
yaqd_rgb-2022.6.0.dist-info/LICENSE_RGBDRIVERKIT
yaqd_rgb-2022.6.0.dist-info/WHEEL
yaqd_rgb-2022.6.0.dist-info/METADATA
yaqd_rgb-2022.6.0.dist-info/RECORD
