Metadata-Version: 2.1
Name: yaqd-rgb
Version: 2022.6.0
Summary: yaq daemons for RGB Photonics hardware
Home-page: https://yaq.fyi
Author: yaq developers
Requires-Python: >=3.7
Classifier: Development Status :: 2 - Pre-Alpha
Classifier: Intended Audience :: Science/Research
Classifier: License :: OSI Approved :: BSD License
Classifier: Natural Language :: English
Classifier: Programming Language :: Python :: 3
Classifier: Programming Language :: Python :: 3.7
Classifier: Programming Language :: Python :: 3.8
Classifier: Topic :: Scientific/Engineering
Requires-Dist: numpy
Requires-Dist: pyusb
Requires-Dist: yaqd-core>=2020.06.3
Requires-Dist: black ; extra == "dev"
Requires-Dist: pre-commit ; extra == "dev"
Project-URL: Issues, https://github.com/yaq-project/yaqd-rgb/issues
Project-URL: Source, https://github.com/yaq-project/yaqd-rgb
Provides-Extra: dev
